napalm_ce/__init__.py
napalm_ce/ce.py
napalm_ce/utils/__init__.py
napalm_ce-0.2.0.dist-info/LICENSE
napalm_ce-0.2.0.dist-info/METADATA
napalm_ce-0.2.0.dist-info/WHEEL
napalm_ce-0.2.0.dist-info/top_level.txt
napalm_ce-0.2.0.dist-info/RECORD
