Metadata-Version: 2.1
Name: napalm-ce
Version: 0.2.0
Summary: NAPALM driver for Huawei CloudEngine switches
Home-page: https://github.com/napalm-automation-community/napalm-ce
Author: Hao Tang
Author-email: thddaniel92@gmail.com
License: Apache 2.0
Platform: UNKNOWN
Classifier: Topic :: Utilities
Classifier: License :: OSI Approved :: Apache Software License
Classifier: Programming Language :: Python
Classifier: Programming Language :: Python :: 3
Classifier: Programming Language :: Python :: 3.6
Classifier: Programming Language :: Python :: 3.7
Classifier: Programming Language :: Python :: 3.8
Classifier: Operating System :: POSIX :: Linux
Classifier: Operating System :: MacOS
Requires-Dist: napalm (>=3.0.0)
Requires-Dist: setuptools (>=38.4.0)
Requires-Dist: netmiko (>=3.1.0)
Requires-Dist: paramiko (>=2.6.0)
Requires-Dist: requests (>=2.7.0)
Requires-Dist: future
Requires-Dist: jinja2
